stackit/redis/__init__.py
stackit/redis/api/__init__.py
stackit/redis/api/default_api.py
stackit/redis/api_client.py
stackit/redis/api_response.py
stackit/redis/configuration.py
stackit/redis/exceptions.py
stackit/redis/models/__init__.py
stackit/redis/models/backup.py
stackit/redis/models/create_backup_response_item.py
stackit/redis/models/create_instance_payload.py
stackit/redis/models/create_instance_response.py
stackit/redis/models/credentials.py
stackit/redis/models/credentials_list_item.py
stackit/redis/models/credentials_response.py
stackit/redis/models/error.py
stackit/redis/models/get_metrics_response.py
stackit/redis/models/instance.py
stackit/redis/models/instance_last_operation.py
stackit/redis/models/instance_parameters.py
stackit/redis/models/instance_schema.py
stackit/redis/models/list_backups_response.py
stackit/redis/models/list_credentials_response.py
stackit/redis/models/list_instances_response.py
stackit/redis/models/list_offerings_response.py
stackit/redis/models/list_restores_response.py
stackit/redis/models/model_schema.py
stackit/redis/models/offering.py
stackit/redis/models/partial_update_instance_payload.py
stackit/redis/models/plan.py
stackit/redis/models/raw_credentials.py
stackit/redis/models/restore.py
stackit/redis/models/trigger_restore_response.py
stackit/redis/models/update_backups_config_payload.py
stackit/redis/models/update_backups_config_response.py
stackit/redis/py.typed
stackit/redis/rest.py
stackit_redis-0.3.0.dist-info/LICENSE.md
stackit_redis-0.3.0.dist-info/METADATA
stackit_redis-0.3.0.dist-info/NOTICE.txt
stackit_redis-0.3.0.dist-info/WHEEL
stackit_redis-0.3.0.dist-info/RECORD
